{
  "taskDefinitionArn": "arn:aws:ecs:ap-southeast-2:949018088476:task-definition/rice-disease-app:1",
  "containerDefinitions": [
    {
      "name": "rice-disease-app",
      "image": "949018088476.dkr.ecr.ap-southeast-2.amazonaws.com/rice-disease-app:latest",
      "cpu": 0,
      "portMappings": [
        {
          "name": "rice-disease-app-8501-tcp",
          "containerPort": 8501,
          "hostPort": 8501,
          "protocol": "tcp",
          "appProtocol": "http"
        }
      ],
      "essential": true,
      "environment": [],
      "environmentFiles": [],
      "mountPoints": [],
      "volumesFrom": [],
      "ulimits": [],
      "logConfiguration": {
        "logDriver": "awslogs",
        "options": {
          "awslogs-group": "/ecs/rice-disease-app",
          "mode": "non-blocking",
          "awslogs-create-group": "true",
          "max-buffer-size": "25m",
          "awslogs-region": "ap-southeast-2",
          "awslogs-stream-prefix": "ecs"
        },
        "secretOptions": []
      },
      "systemControls": []
    }
  ],
  "family": "rice-disease-app",
  "executionRoleArn": "arn:aws:iam::949018088476:role/ecsTaskExecutionRole",
  "networkMode": "awsvpc",
  "revision": 1,
  "volumes": [],
  "status": "ACTIVE",
  "requiresAttributes": [
    {
      "name": "com.amazonaws.ecs.capability.logging-driver.awslogs"
    },
    {
      "name": "ecs.capability.execution-role-awslogs"
    },
    {
      "name": "com.amazonaws.ecs.capability.ecr-auth"
    },
    {
      "name": "com.amazonaws.ecs.capability.docker-remote-api.1.19"
    },
    {
      "name": "com.amazonaws.ecs.capability.docker-remote-api.1.28"
    },
    {
      "name": "ecs.capability.execution-role-ecr-pull"
    },
    {
      "name": "ecs.capability.extensible-ephemeral-storage"
    },
    {
      "name": "com.amazonaws.ecs.capability.docker-remote-api.1.18"
    },
    {
      "name": "ecs.capability.task-eni"
    },
    {
      "name": "com.amazonaws.ecs.capability.docker-remote-api.1.29"
    }
  ],
  "placementConstraints": [],
  "compatibilities": ["EC2", "FARGATE"],
  "requiresCompatibilities": ["FARGATE"],
  "cpu": "1024",
  "memory": "3072",
  "ephemeralStorage": {
    "sizeInGiB": 21
  },
  "runtimePlatform": {
    "cpuArchitecture": "X86_64",
    "operatingSystemFamily": "LINUX"
  },
  "registeredAt": "2025-06-02T15:15:04.062Z",
  "registeredBy": "arn:aws:iam::949018088476:root",
  "enableFaultInjection": false,
  "tags": []
}
